<?xml version="1.0"?>
<game_state>
	<input />
	<controls>
		<debug map="68" gui="67" entities="66" next_round="65" spawn_blue_dog="64" spawn_blue_chrono="63" spawn_blue_sniper="62" spawn_red_chrono="61" spawn_red_desolator="60" spawn_red_bazooka="59" spawn_red_conscript="58" />
		<mouse select="1" issue_orders="3" />
		<camera up="26" down="22" left="4" right="7" />
		<orders hold="44" hunt="20" patrol="8" defensive="225" aggressive="224" />
	</controls>
	<window />
	<textures />
	<map />
	<pathfinding />
	<scene />
	<entities heavy_units_unlocked="false" unit_buff="false" buildings_buff="false" income_buff1="false" income_buff2="false" income_buff3="false">
		<units active="20">
			<unit_0 position_x="167.509567" position_y="818.781128" faction="0" type="2">
				<stats health="6" damage="2" cadency="1" attack_radius="150" vision_radius="300" lin_speed="90" />
				<unit infantry_type="1" orders="0" aggro="1" provoqued="false" origin_x="179" origin_y="853" destination_x="179" destination_y="853" />
			</unit_0>
			<unit_1 position_x="197.657852" position_y="834.155579" faction="0" type="2">
				<stats health="40" damage="4" cadency="1" attack_radius="200" vision_radius="300" lin_speed="60" />
				<unit infantry_type="4" orders="0" aggro="1" provoqued="false" origin_x="209" origin_y="869" destination_x="209" destination_y="869" />
			</unit_1>
			<unit_2 position_x="499.036774" position_y="414.394531" faction="1" type="2">
				<stats health="6" damage="2" cadency="0.5" attack_radius="150" vision_radius="200" lin_speed="90" />
				<unit infantry_type="0" orders="0" aggro="2" provoqued="false" origin_x="511" origin_y="449" destination_x="511" destination_y="449" />
			</unit_2>
			<unit_3 position_x="528.200195" position_y="435" faction="1" type="2">
				<stats health="6" damage="2" cadency="0.5" attack_radius="150" vision_radius="200" lin_speed="90" />
				<unit infantry_type="0" orders="0" aggro="2" provoqued="false" origin_x="522" origin_y="470" destination_x="540" destination_y="450" />
			</unit_3>
			<unit_4 position_x="461.34375" position_y="433.755157" faction="1" type="2">
				<stats health="6" damage="2" cadency="0.5" attack_radius="150" vision_radius="200" lin_speed="90" />
				<unit infantry_type="0" orders="0" aggro="2" provoqued="false" origin_x="479" origin_y="468" destination_x="479" destination_y="468" />
			</unit_4>
			<unit_5 position_x="466.956512" position_y="413.796875" faction="1" type="2">
				<stats health="6" damage="2" cadency="0.5" attack_radius="150" vision_radius="200" lin_speed="90" />
				<unit infantry_type="0" orders="0" aggro="2" provoqued="false" origin_x="478" origin_y="448" destination_x="478" destination_y="448" />
			</unit_5>
			<unit_6 position_x="528.64801" position_y="409.628784" faction="1" type="2">
				<stats health="6" damage="2" cadency="0.5" attack_radius="150" vision_radius="200" lin_speed="90" />
				<unit infantry_type="0" orders="0" aggro="2" provoqued="false" origin_x="540" origin_y="444" destination_x="540" destination_y="444" />
			</unit_6>
			<unit_7 position_x="558.221863" position_y="438.671143" faction="1" type="2">
				<stats health="6" damage="2" cadency="0.5" attack_radius="150" vision_radius="200" lin_speed="90" />
				<unit infantry_type="0" orders="0" aggro="2" provoqued="false" origin_x="570" origin_y="473" destination_x="570" destination_y="473" />
			</unit_7>
			<unit_8 position_x="-1659.16382" position_y="894.394531" faction="1" type="2">
				<stats health="6" damage="2" cadency="0.5" attack_radius="150" vision_radius="200" lin_speed="90" />
				<unit infantry_type="0" orders="0" aggro="2" provoqued="false" origin_x="-1647" origin_y="929" destination_x="-1647" destination_y="929" />
			</unit_8>
			<unit_9 position_x="-88.2110977" position_y="1188.10461" faction="0" type="2">
				<stats health="6" damage="2" cadency="1" attack_radius="150" vision_radius="300" lin_speed="90" />
				<unit infantry_type="1" orders="1" aggro="0" provoqued="true" origin_x="360" origin_y="1245" destination_x="-750" destination_y="1155" />
			</unit_9>
			<unit_10 position_x="143.457367" position_y="1342.724" faction="0" type="2">
				<stats health="6" damage="2" cadency="1" attack_radius="150" vision_radius="300" lin_speed="90" />
				<unit infantry_type="1" orders="1" aggro="1" provoqued="true" origin_x="390" origin_y="1260" destination_x="-840" destination_y="1620" />
			</unit_10>
			<unit_11 position_x="14.2654343" position_y="1136.73462" faction="0" type="2">
				<stats health="40" damage="4" cadency="1" attack_radius="200" vision_radius="300" lin_speed="60" />
				<unit infantry_type="4" orders="1" aggro="0" provoqued="true" origin_x="330" origin_y="1260" destination_x="-720" destination_y="1170" />
			</unit_11>
			<unit_12 position_x="-117.839294" position_y="1202.92053" faction="0" type="2">
				<stats health="4" damage="120" cadency="600" attack_radius="450" vision_radius="600" lin_speed="90" />
				<unit infantry_type="5" orders="1" aggro="0" provoqued="false" origin_x="331" origin_y="1230" destination_x="-780" destination_y="1170" />
			</unit_12>
			<unit_13 position_x="-1649.00049" position_y="915" faction="1" type="2">
				<stats health="6" damage="2" cadency="0.5" attack_radius="150" vision_radius="200" lin_speed="90" />
				<unit infantry_type="0" orders="0" aggro="2" provoqued="false" origin_x="-1638" origin_y="950" destination_x="-1620" destination_y="930" />
			</unit_13>
			<unit_14 position_x="-1698.65625" position_y="913.75531" faction="1" type="2">
				<stats health="6" damage="2" cadency="0.5" attack_radius="150" vision_radius="200" lin_speed="90" />
				<unit infantry_type="0" orders="0" aggro="2" provoqued="false" origin_x="-1680" origin_y="948" destination_x="-1680" destination_y="948" />
			</unit_14>
			<unit_15 position_x="-1692.74988" position_y="892.875" faction="1" type="2">
				<stats health="6" damage="2" cadency="0.5" attack_radius="150" vision_radius="200" lin_speed="90" />
				<unit infantry_type="0" orders="0" aggro="2" provoqued="false" origin_x="-1680" origin_y="927" destination_x="-1680" destination_y="927" />
			</unit_15>
			<unit_16 position_x="-1624.0835" position_y="906.99646" faction="1" type="2">
				<stats health="6" damage="2" cadency="0.5" attack_radius="150" vision_radius="200" lin_speed="90" />
				<unit infantry_type="0" orders="0" aggro="2" provoqued="false" origin_x="-1618" origin_y="941" destination_x="-1618" destination_y="941" />
			</unit_16>
			<unit_17 position_x="-1600.98291" position_y="919.295532" faction="1" type="2">
				<stats health="6" damage="2" cadency="0.5" attack_radius="150" vision_radius="200" lin_speed="90" />
				<unit infantry_type="0" orders="0" aggro="2" provoqued="false" origin_x="-1588" origin_y="954" destination_x="-1588" destination_y="954" />
			</unit_17>
			<unit_18 position_x="-584.086792" position_y="579.855103" faction="1" type="2">
				<stats health="40" damage="4" cadency="1" attack_radius="200" vision_radius="300" lin_speed="60" />
				<unit infantry_type="4" orders="0" aggro="2" provoqued="false" origin_x="-571" origin_y="614" destination_x="-571" destination_y="614" />
			</unit_18>
			<unit_19 position_x="-559.000122" position_y="585" faction="1" type="2">
				<stats health="40" damage="4" cadency="1" attack_radius="200" vision_radius="300" lin_speed="60" />
				<unit infantry_type="4" orders="0" aggro="2" provoqued="false" origin_x="-558" origin_y="620" destination_x="-540" destination_y="600" />
			</unit_19>
		</units>
		<launchers active="0" />
		<buildings active="7">
			<building_7 type="0" faction="0" health="126.377663" max_health="300" repairable="true" reward_given="true" />
			<building_6 type="2" faction="2" health="0" max_health="200" repairable="true" reward_given="false" />
			<building_5 type="1" faction="2" health="0" max_health="200" repairable="true" reward_given="false" />
			<building_4 type="3" faction="2" health="0" max_health="200" repairable="true" reward_given="false" />
			<building_3 type="4" faction="2" health="0" max_health="200" repairable="true" reward_given="false" />
			<building_2 type="5" faction="2" health="0" max_health="200" repairable="true" reward_given="false" />
			<building_1 type="6" faction="2" health="0" max_health="200" repairable="true" reward_given="false" />
		</buildings>
	</entities>
	<audio volume="50">
		<music volume="80" />
		<sfx volume="80" />
	</audio>
	<fonts />
	<user_interface />
	<group_manager />
	<player money="530" income="30" income_timer="1345" income_received="false" />
	<horde_manager>
		<round round_num="2" round_timer="1095" round_threat="30" />
		<horde horde_active="true" max_hordes="10" enemies_left="14" clean_hordes_timer="1095" />
		<threat threat_incremental="15" inital_threat_incremental="15" initial_round_threat="10" />
		<spawns>
			<spawn_1 active="false" enemies_attacking="false" spawn_time="91587" />
			<spawn_2 active="false" enemies_attacking="true" spawn_time="81666" />
			<spawn_3 active="false" enemies_attacking="false" spawn_time="91587" />
			<spawn_4 active="false" enemies_attacking="true" spawn_time="81665" />
			<spawn_5 active="false" enemies_attacking="false" spawn_time="91587" />
			<spawn_6 active="false" enemies_attacking="true" spawn_time="81665" />
			<spawn_7 active="false" enemies_attacking="false" spawn_time="91587" />
			<spawn_8 active="true" enemies_attacking="false" spawn_time="1095" />
			<spawn_9 active="false" enemies_attacking="false" spawn_time="91587" />
			<spawn_10 active="true" enemies_attacking="false" spawn_time="1093" />
			<spawn_11 active="true" enemies_attacking="false" spawn_time="1092" />
			<spawn_12 active="false" enemies_attacking="false" spawn_time="91587" />
		</spawns>
	</horde_manager>
	<minimap />
	<renderer>
		<camera x="" y="" />
	</renderer>
</game_state>
